setup.py
bin/lambda2
lambda2/__init__.py
lambda2/config.py
lambda2/content_less_api.py
lambda2/discover.py
lambda2/driver.py
lambda2/function_pool.py
lambda2/hash_ring.py
lambda2/lambad2.py
lambda2/lambda2_hash.py
lambda2/lambda_server_adapter.py
lambda2/main.py
lambda2/result_pool.py
lambda2/scoket_adapter.py
lambda2/server.py
lambda2/subscriber.py
lambda2.egg-info/PKG-INFO
lambda2.egg-info/SOURCES.txt
lambda2.egg-info/dependency_links.txt
lambda2.egg-info/entry_points.txt
lambda2.egg-info/requires.txt
lambda2.egg-info/top_level.txt