Metadata-Version: 1.1
Name: lambda2
Version: 0.1.1
Summary: 简单的分布式计算引擎
Home-page: https://github.com/xxlv/lambda2
Author: ghost
Author-email: lvxiang119@gmail.com
License: MIT
Platform: UNKNOWN
Classifier: Intended Audience :: System Administrators
Classifier: Programming Language :: Python :: 3
